sqlflow/__init__.py
sqlflow/__main__.py
sqlflow/_version.py
sqlflow/client.py
sqlflow/compound_message.py
sqlflow/env_expand.py
sqlflow/magic.py
sqlflow/rows.py
sqlflow/proto/sqlflow_pb2.py
sqlflow/proto/sqlflow_pb2_grpc.py
sqlflowcli-0.15.2.dist-info/LICENSE
sqlflowcli-0.15.2.dist-info/METADATA
sqlflowcli-0.15.2.dist-info/WHEEL
sqlflowcli-0.15.2.dist-info/entry_points.txt
sqlflowcli-0.15.2.dist-info/top_level.txt
sqlflowcli-0.15.2.dist-info/RECORD
