Metadata-Version: 2.1
Name: sqlflowcli
Version: 0.15.2
Summary: SQLFlow client library for Python.
Home-page: https://github.com/sql-machine-learning/sqlflow
Author: typhoonzero
Author-email: typhoonzero1986@gmail.com
License: Apache License 2.0
Classifier: License :: OSI Approved :: Apache Software License
Classifier: Programming Language :: Python
Classifier: Programming Language :: Python :: 3 :: Only
Classifier: Programming Language :: Python :: 3.5
Classifier: Programming Language :: Python :: 3.6
Classifier: Programming Language :: Python :: 3.7
Classifier: Programming Language :: Python :: Implementation :: CPython
Classifier: Programming Language :: Python :: Implementation :: PyPy
Requires-Python: >=3.5.0
License-File: LICENSE
Requires-Dist: protobuf (<4,>=3.7.1)
Requires-Dist: grpcio (<2,>=1.17)
Requires-Dist: ipython (>=7.9)
Requires-Dist: pandas
Requires-Dist: tornado (>=6.0.0)
Requires-Dist: python-dotenv (>0.10.0)
Requires-Dist: nest-asyncio (>=1.4.0)
